enhsp_wrapper/__init__.py
enhsp_wrapper/enhsp.py
enhsp_wrapper/lib/README.TXT
enhsp_wrapper/lib/__init__.py
enhsp_wrapper/lib/jpddlplus.jar
enhsp_wrapper/lib/lib/antlr-3.4-complete.jar
enhsp_wrapper/lib/lib/commons-cli-1.4.jar
enhsp_wrapper/lib/lib/commons-collections4-4.3.jar
enhsp_wrapper/lib/lib/cplex.jar
enhsp_wrapper/lib/lib/fastutil-8.3.1.jar
enhsp_wrapper/lib/lib/guava-26.0-jre.jar
enhsp_wrapper/lib/lib/hppc-0.8.0-SNAPSHOT.jar
enhsp_wrapper/lib/lib/ia_math.jar
enhsp_wrapper/lib/lib/jgrapht-bundle-1.3.0.jar
enhsp_wrapper/lib/lib/jinterval-0.1.jar
enhsp_wrapper/lib/lib/json-simple-1.1.1.jar
enhsp_wrapper-0.1.4.dist-info/LICENSE
enhsp_wrapper-0.1.4.dist-info/METADATA
enhsp_wrapper-0.1.4.dist-info/WHEEL
enhsp_wrapper-0.1.4.dist-info/RECORD
