Metadata-Version: 2.1
Name: enhsp-wrapper
Version: 0.1.4
Summary: Wrapper for the ENHSP planner
Home-page: https://gitlab.anu.edu.au/u6937003/enhsp_wrapper
License: MIT
Author: Ryan Wang
Author-email: ryanxiaowang2001@gmail.com
Requires-Python: >=3.8,<4.0
Classifier: License :: OSI Approved :: MIT License
Classifier: Programming Language :: Python :: 3
Classifier: Programming Language :: Python :: 3.8
Classifier: Programming Language :: Python :: 3.9
Classifier: Programming Language :: Python :: 3.10
Classifier: Programming Language :: Python :: 3.11
Requires-Dist: JPype1 (>=1.4.1,<2.0.0)
Project-URL: Repository, https://gitlab.anu.edu.au/u6937003/enhsp_wrapper
